[
  {
    "MovimientoID": 59,
    "ProductoID": 1,
    "Tipo": "ENTRADA",
    "Cantidad": 50,
    "Fecha": "2025-10-17",
    "StockAntesMov": 160,
    "StockDespMov": 210,
    "CostoUnitario": 10.00,
    "Referencia": "asdasdas",
    "Observaciones": "trabajo"
  },
  {
    "MovimientoID": 60,
    "ProductoID": 1,
    "Tipo": "ENTRADA",
    "Cantidad": 10,
    "Fecha": "2025-10-17",
    "StockAntesMov": 210,
    "StockDespMov": 220,
    "CostoUnitario": 50.00,
    "Referencia": "851265126230",
    "Observaciones": "kjhgfds"
  },
  {
    "MovimientoID": 61,
    "ProductoID": 1,
    "Tipo": "ENTRADA",
    "Cantidad": 10,
    "Fecha": "2025-10-17",
    "StockAntesMov": 220,
    "StockDespMov": 230,
    "CostoUnitario": 50.00,
    "Referencia": "asdasda",
    "Observaciones": "sdasd"
  },
  {
    "MovimientoID": 62,
    "ProductoID": 1,
    "Tipo": "ENTRADA",
    "Cantidad": 50,
    "Fecha": "2025-10-17",
    "StockAntesMov": 230,
    "StockDespMov": 280,
    "CostoUnitario": 60.00,
    "Referencia": "5a1s3d",
    "Observaciones": "sdasd"
  }
]