[
  {
    "MovimientoID": 5283,
    "ProductoID": 1,
    "Tipo": "SALIDA",
    "Cantidad": 1,
    "Fecha": "2026-01-05",
    "StockAntesMov": 944,
    "StockDespMov": 943,
    "CostoUnitario": 0.00,
    "Referencia": "salidaxventa",
    "Observaciones": "Venta"
  },
  {
    "MovimientoID": 5284,
    "ProductoID": 2,
    "Tipo": "SALIDA",
    "Cantidad": 1,
    "Fecha": "2026-01-05",
    "StockAntesMov": 114,
    "StockDespMov": 113,
    "CostoUnitario": 0.00,
    "Referencia": "salidaxventa",
    "Observaciones": "Venta"
  },
  {
    "MovimientoID": 5285,
    "ProductoID": 1,
    "Tipo": "SALIDA",
    "Cantidad": 2,
    "Fecha": "2026-01-05",
    "StockAntesMov": 943,
    "StockDespMov": 941,
    "CostoUnitario": 0.00,
    "Referencia": "salidaxventa",
    "Observaciones": "Venta"
  },
  {
    "MovimientoID": 5286,
    "ProductoID": 1,
    "Tipo": "SALIDA",
    "Cantidad": 55,
    "Fecha": "2026-01-05",
    "StockAntesMov": 941,
    "StockDespMov": 886,
    "CostoUnitario": 0.00,
    "Referencia": "salidaxventa",
    "Observaciones": "Venta"
  },
  {
    "MovimientoID": 5287,
    "ProductoID": 2,
    "Tipo": "SALIDA",
    "Cantidad": 35,
    "Fecha": "2026-01-05",
    "StockAntesMov": 113,
    "StockDespMov": 78,
    "CostoUnitario": 0.00,
    "Referencia": "salidaxventa",
    "Observaciones": "Venta"
  },
  {
    "MovimientoID": 5288,
    "ProductoID": 1,
    "Tipo": "SALIDA",
    "Cantidad": 1,
    "Fecha": "2026-01-05",
    "StockAntesMov": 886,
    "StockDespMov": 885,
    "CostoUnitario": 0.00,
    "Referencia": "salidaxventa",
    "Observaciones": "Venta"
  },
  {
    "MovimientoID": 5289,
    "ProductoID": 1,
    "Tipo": "SALIDA",
    "Cantidad": 2,
    "Fecha": "2026-01-05",
    "StockAntesMov": 885,
    "StockDespMov": 883,
    "CostoUnitario": 0.00,
    "Referencia": "salidaxventa",
    "Observaciones": "Venta"
  },
  {
    "MovimientoID": 5290,
    "ProductoID": 1,
    "Tipo": "SALIDA",
    "Cantidad": 1,
    "Fecha": "2026-01-05",
    "StockAntesMov": 883,
    "StockDespMov": 882,
    "CostoUnitario": 0.00,
    "Referencia": "salidaxventa",
    "Observaciones": "Venta"
  },
  {
    "MovimientoID": 5291,
    "ProductoID": 1,
    "Tipo": "SALIDA",
    "Cantidad": 3,
    "Fecha": "2026-01-06",
    "StockAntesMov": 882,
    "StockDespMov": 879,
    "CostoUnitario": 0.00,
    "Referencia": "salidaxventa",
    "Observaciones": "Venta"
  },
  {
    "MovimientoID": 5292,
    "ProductoID": 1,
    "Tipo": "SALIDA",
    "Cantidad": 1,
    "Fecha": "2026-01-06",
    "StockAntesMov": 879,
    "StockDespMov": 878,
    "CostoUnitario": 0.00,
    "Referencia": "salidaxventa",
    "Observaciones": "Venta"
  },
  {
    "MovimientoID": 5293,
    "ProductoID": 1,
    "Tipo": "SALIDA",
    "Cantidad": 4,
    "Fecha": "2026-01-07",
    "StockAntesMov": 878,
    "StockDespMov": 874,
    "CostoUnitario": 0.00,
    "Referencia": "salidaxventa",
    "Observaciones": "Venta"
  },
  {
    "MovimientoID": 5294,
    "ProductoID": 1,
    "Tipo": "SALIDA",
    "Cantidad": 2,
    "Fecha": "2026-01-07",
    "StockAntesMov": 874,
    "StockDespMov": 872,
    "CostoUnitario": 0.00,
    "Referencia": "salidaxventa",
    "Observaciones": "Venta"
  },
  {
    "MovimientoID": 5295,
    "ProductoID": 1,
    "Tipo": "SALIDA",
    "Cantidad": 1,
    "Fecha": "2026-01-07",
    "StockAntesMov": 872,
    "StockDespMov": 871,
    "CostoUnitario": 0.00,
    "Referencia": "salidaxventa",
    "Observaciones": "Venta"
  },
  {
    "MovimientoID": 5296,
    "ProductoID": 1,
    "Tipo": "SALIDA",
    "Cantidad": 14,
    "Fecha": "2026-01-07",
    "StockAntesMov": 871,
    "StockDespMov": 857,
    "CostoUnitario": 0.00,
    "Referencia": "salidaxventa",
    "Observaciones": "Venta"
  },
  {
    "MovimientoID": 5297,
    "ProductoID": 1,
    "Tipo": "SALIDA",
    "Cantidad": 2,
    "Fecha": "2026-01-07",
    "StockAntesMov": 857,
    "StockDespMov": 855,
    "CostoUnitario": 0.00,
    "Referencia": "salidaxventa",
    "Observaciones": "Venta"
  },
  {
    "MovimientoID": 5298,
    "ProductoID": 1,
    "Tipo": "SALIDA",
    "Cantidad": 2,
    "Fecha": "2026-01-07",
    "StockAntesMov": 855,
    "StockDespMov": 853,
    "CostoUnitario": 0.00,
    "Referencia": "salidaxventa",
    "Observaciones": "Venta"
  },
  {
    "MovimientoID": 5299,
    "ProductoID": 1,
    "Tipo": "SALIDA",
    "Cantidad": 1,
    "Fecha": "2026-01-07",
    "StockAntesMov": 853,
    "StockDespMov": 852,
    "CostoUnitario": 0.00,
    "Referencia": "salidaxventa",
    "Observaciones": "Venta"
  },
  {
    "MovimientoID": 5300,
    "ProductoID": 1,
    "Tipo": "SALIDA",
    "Cantidad": 1,
    "Fecha": "2026-01-07",
    "StockAntesMov": 852,
    "StockDespMov": 851,
    "CostoUnitario": 0.00,
    "Referencia": "salidaxventa",
    "Observaciones": "Venta"
  },
  {
    "MovimientoID": 5301,
    "ProductoID": 2,
    "Tipo": "SALIDA",
    "Cantidad": 1,
    "Fecha": "2026-01-07",
    "StockAntesMov": 78,
    "StockDespMov": 77,
    "CostoUnitario": 0.00,
    "Referencia": "salidaxventa",
    "Observaciones": "Venta"
  },
  {
    "MovimientoID": 5302,
    "ProductoID": 1,
    "Tipo": "SALIDA",
    "Cantidad": 1,
    "Fecha": "2026-01-07",
    "StockAntesMov": 851,
    "StockDespMov": 850,
    "CostoUnitario": 0.00,
    "Referencia": "salidaxventa",
    "Observaciones": "Venta"
  },
  {
    "MovimientoID": 5303,
    "ProductoID": 1,
    "Tipo": "SALIDA",
    "Cantidad": 2,
    "Fecha": "2026-01-08",
    "StockAntesMov": 850,
    "StockDespMov": 848,
    "CostoUnitario": 0.00,
    "Referencia": "salidaxventa",
    "Observaciones": "Venta"
  },
  {
    "MovimientoID": 5304,
    "ProductoID": 1,
    "Tipo": "SALIDA",
    "Cantidad": 1,
    "Fecha": "2026-01-08",
    "StockAntesMov": 848,
    "StockDespMov": 847,
    "CostoUnitario": 0.00,
    "Referencia": "salidaxventa",
    "Observaciones": "Venta"
  },
  {
    "MovimientoID": 5305,
    "ProductoID": 1,
    "Tipo": "SALIDA",
    "Cantidad": 2,
    "Fecha": "2026-01-08",
    "StockAntesMov": 847,
    "StockDespMov": 845,
    "CostoUnitario": 0.00,
    "Referencia": "salidaxventa",
    "Observaciones": "Venta"
  },
  {
    "MovimientoID": 5306,
    "ProductoID": 1,
    "Tipo": "SALIDA",
    "Cantidad": 3,
    "Fecha": "2026-01-08",
    "StockAntesMov": 845,
    "StockDespMov": 842,
    "CostoUnitario": 0.00,
    "Referencia": "salidaxventa",
    "Observaciones": "Venta"
  },
  {
    "MovimientoID": 5307,
    "ProductoID": 2,
    "Tipo": "SALIDA",
    "Cantidad": 1,
    "Fecha": "2026-01-08",
    "StockAntesMov": 77,
    "StockDespMov": 76,
    "CostoUnitario": 0.00,
    "Referencia": "salidaxventa",
    "Observaciones": "Venta"
  },
  {
    "MovimientoID": 5308,
    "ProductoID": 1,
    "Tipo": "SALIDA",
    "Cantidad": 5,
    "Fecha": "2026-01-08",
    "StockAntesMov": 842,
    "StockDespMov": 837,
    "CostoUnitario": 0.00,
    "Referencia": "salidaxventa",
    "Observaciones": "Venta"
  },
  {
    "MovimientoID": 5309,
    "ProductoID": 2,
    "Tipo": "SALIDA",
    "Cantidad": 1,
    "Fecha": "2026-01-12",
    "StockAntesMov": 76,
    "StockDespMov": 75,
    "CostoUnitario": 0.00,
    "Referencia": "salidaxventa",
    "Observaciones": "Venta"
  },
  {
    "MovimientoID": 5310,
    "ProductoID": 1,
    "Tipo": "SALIDA",
    "Cantidad": 4,
    "Fecha": "2026-01-12",
    "StockAntesMov": 837,
    "StockDespMov": 833,
    "CostoUnitario": 0.00,
    "Referencia": "salidaxventa",
    "Observaciones": "Venta"
  },
  {
    "MovimientoID": 5311,
    "ProductoID": 3,
    "Tipo": "SALIDA",
    "Cantidad": 1,
    "Fecha": "2026-01-12",
    "StockAntesMov": 56,
    "StockDespMov": 55,
    "CostoUnitario": 0.00,
    "Referencia": "salidaxventa",
    "Observaciones": "Venta"
  },
  {
    "MovimientoID": 5312,
    "ProductoID": 1,
    "Tipo": "SALIDA",
    "Cantidad": 1,
    "Fecha": "2026-01-12",
    "StockAntesMov": 833,
    "StockDespMov": 832,
    "CostoUnitario": 0.00,
    "Referencia": "salidaxventa",
    "Observaciones": "Venta"
  },
  {
    "MovimientoID": 5313,
    "ProductoID": 1,
    "Tipo": "SALIDA",
    "Cantidad": 15,
    "Fecha": "2026-01-12",
    "StockAntesMov": 832,
    "StockDespMov": 817,
    "CostoUnitario": 0.00,
    "Referencia": "salidaxventa",
    "Observaciones": "Venta"
  },
  {
    "MovimientoID": 5314,
    "ProductoID": 2,
    "Tipo": "SALIDA",
    "Cantidad": 2,
    "Fecha": "2026-01-12",
    "StockAntesMov": 75,
    "StockDespMov": 73,
    "CostoUnitario": 0.00,
    "Referencia": "salidaxventa",
    "Observaciones": "Venta"
  },
  {
    "MovimientoID": 5315,
    "ProductoID": 3,
    "Tipo": "SALIDA",
    "Cantidad": 12,
    "Fecha": "2026-01-12",
    "StockAntesMov": 55,
    "StockDespMov": 43,
    "CostoUnitario": 0.00,
    "Referencia": "salidaxventa",
    "Observaciones": "Venta"
  },
  {
    "MovimientoID": 5316,
    "ProductoID": 3,
    "Tipo": "SALIDA",
    "Cantidad": 12,
    "Fecha": "2026-01-12",
    "StockAntesMov": 43,
    "StockDespMov": 31,
    "CostoUnitario": 0.00,
    "Referencia": "salidaxventa",
    "Observaciones": "Venta"
  },
  {
    "MovimientoID": 5317,
    "ProductoID": 2,
    "Tipo": "SALIDA",
    "Cantidad": 2,
    "Fecha": "2026-01-14",
    "StockAntesMov": 73,
    "StockDespMov": 71,
    "CostoUnitario": 0.00,
    "Referencia": "salidaxventa",
    "Observaciones": "Venta"
  },
  {
    "MovimientoID": 5318,
    "ProductoID": 1,
    "Tipo": "SALIDA",
    "Cantidad": 1,
    "Fecha": "2026-01-14",
    "StockAntesMov": 817,
    "StockDespMov": 816,
    "CostoUnitario": 0.00,
    "Referencia": "salidaxventa",
    "Observaciones": "Venta"
  },
  {
    "MovimientoID": 5319,
    "ProductoID": 1,
    "Tipo": "SALIDA",
    "Cantidad": 20,
    "Fecha": "2026-01-14",
    "StockAntesMov": 816,
    "StockDespMov": 796,
    "CostoUnitario": 0.00,
    "Referencia": "salidaxventa",
    "Observaciones": "Venta"
  },
  {
    "MovimientoID": 5320,
    "ProductoID": 1,
    "Tipo": "SALIDA",
    "Cantidad": 5,
    "Fecha": "2026-01-14",
    "StockAntesMov": 796,
    "StockDespMov": 791,
    "CostoUnitario": 0.00,
    "Referencia": "salidaxventa",
    "Observaciones": "Venta"
  },
  {
    "MovimientoID": 5321,
    "ProductoID": 1,
    "Tipo": "SALIDA",
    "Cantidad": 1,
    "Fecha": "2026-01-14",
    "StockAntesMov": 791,
    "StockDespMov": 790,
    "CostoUnitario": 0.00,
    "Referencia": "salidaxventa",
    "Observaciones": "Venta"
  },
  {
    "MovimientoID": 5322,
    "ProductoID": 2,
    "Tipo": "SALIDA",
    "Cantidad": 1,
    "Fecha": "2026-01-14",
    "StockAntesMov": 71,
    "StockDespMov": 70,
    "CostoUnitario": 0.00,
    "Referencia": "salidaxventa",
    "Observaciones": "Venta"
  },
  {
    "MovimientoID": 5323,
    "ProductoID": 3,
    "Tipo": "SALIDA",
    "Cantidad": 1,
    "Fecha": "2026-01-14",
    "StockAntesMov": 31,
    "StockDespMov": 30,
    "CostoUnitario": 0.00,
    "Referencia": "salidaxventa",
    "Observaciones": "Venta"
  },
  {
    "MovimientoID": 5324,
    "ProductoID": 4,
    "Tipo": "SALIDA",
    "Cantidad": 1,
    "Fecha": "2026-01-14",
    "StockAntesMov": 90,
    "StockDespMov": 89,
    "CostoUnitario": 0.00,
    "Referencia": "salidaxventa",
    "Observaciones": "Venta"
  },
  {
    "MovimientoID": 5325,
    "ProductoID": 1,
    "Tipo": "SALIDA",
    "Cantidad": 1,
    "Fecha": "2026-01-14",
    "StockAntesMov": 790,
    "StockDespMov": 789,
    "CostoUnitario": 0.00,
    "Referencia": "salidaxventa",
    "Observaciones": "Venta"
  },
  {
    "MovimientoID": 5326,
    "ProductoID": 3,
    "Tipo": "SALIDA",
    "Cantidad": 6,
    "Fecha": "2026-01-14",
    "StockAntesMov": 30,
    "StockDespMov": 24,
    "CostoUnitario": 0.00,
    "Referencia": "salidaxventa",
    "Observaciones": "Venta"
  },
  {
    "MovimientoID": 5327,
    "ProductoID": 4,
    "Tipo": "SALIDA",
    "Cantidad": 10,
    "Fecha": "2026-01-14",
    "StockAntesMov": 89,
    "StockDespMov": 79,
    "CostoUnitario": 0.00,
    "Referencia": "salidaxventa",
    "Observaciones": "Venta"
  },
  {
    "MovimientoID": 5328,
    "ProductoID": 3,
    "Tipo": "SALIDA",
    "Cantidad": 8,
    "Fecha": "2026-01-14",
    "StockAntesMov": 24,
    "StockDespMov": 16,
    "CostoUnitario": 0.00,
    "Referencia": "salidaxventa",
    "Observaciones": "Venta"
  },
  {
    "MovimientoID": 5329,
    "ProductoID": 1,
    "Tipo": "SALIDA",
    "Cantidad": 2,
    "Fecha": "2026-01-15",
    "StockAntesMov": 789,
    "StockDespMov": 787,
    "CostoUnitario": 0.00,
    "Referencia": "salidaxventa",
    "Observaciones": "Venta"
  },
  {
    "MovimientoID": 5330,
    "ProductoID": 1,
    "Tipo": "SALIDA",
    "Cantidad": 1,
    "Fecha": "2026-01-15",
    "StockAntesMov": 787,
    "StockDespMov": 786,
    "CostoUnitario": 0.00,
    "Referencia": "salidaxventa",
    "Observaciones": "Venta"
  },
  {
    "MovimientoID": 5331,
    "ProductoID": 1,
    "Tipo": "SALIDA",
    "Cantidad": 1,
    "Fecha": "2026-01-15",
    "StockAntesMov": 786,
    "StockDespMov": 785,
    "CostoUnitario": 0.00,
    "Referencia": "salidaxventa",
    "Observaciones": "Venta"
  },
  {
    "MovimientoID": 5332,
    "ProductoID": 5,
    "Tipo": "ENTRADA",
    "Cantidad": 3,
    "Fecha": "2026-01-15",
    "StockAntesMov": 0,
    "StockDespMov": 3,
    "CostoUnitario": 0.00,
    "Referencia": "nuevos 15/01/26",
    "Observaciones": "tapanosa"
  },
  {
    "MovimientoID": 5333,
    "ProductoID": 3,
    "Tipo": "ENTRADA",
    "Cantidad": 100,
    "Fecha": "2026-01-15",
    "StockAntesMov": 16,
    "StockDespMov": 116,
    "CostoUnitario": 0.00,
    "Referencia": "nuevos 15/01/26",
    "Observaciones": "tapanosa"
  },
  {
    "MovimientoID": 5334,
    "ProductoID": 1,
    "Tipo": "SALIDA",
    "Cantidad": 2,
    "Fecha": "2026-01-15",
    "StockAntesMov": 785,
    "StockDespMov": 783,
    "CostoUnitario": 0.00,
    "Referencia": "salidaxventa",
    "Observaciones": "Venta"
  },
  {
    "MovimientoID": 5335,
    "ProductoID": 1,
    "Tipo": "SALIDA",
    "Cantidad": 1,
    "Fecha": "2026-01-17",
    "StockAntesMov": 783,
    "StockDespMov": 782,
    "CostoUnitario": 0.00,
    "Referencia": "salidaxventa",
    "Observaciones": "Venta"
  },
  {
    "MovimientoID": 5336,
    "ProductoID": 1,
    "Tipo": "SALIDA",
    "Cantidad": 2,
    "Fecha": "2026-01-17",
    "StockAntesMov": 782,
    "StockDespMov": 780,
    "CostoUnitario": 0.00,
    "Referencia": "salidaxventa",
    "Observaciones": "Venta"
  },
  {
    "MovimientoID": 5337,
    "ProductoID": 1,
    "Tipo": "SALIDA",
    "Cantidad": 1,
    "Fecha": "2026-01-17",
    "StockAntesMov": 780,
    "StockDespMov": 779,
    "CostoUnitario": 0.00,
    "Referencia": "salidaxventa",
    "Observaciones": "Venta"
  },
  {
    "MovimientoID": 5338,
    "ProductoID": 2,
    "Tipo": "SALIDA",
    "Cantidad": 1,
    "Fecha": "2026-01-17",
    "StockAntesMov": 70,
    "StockDespMov": 69,
    "CostoUnitario": 0.00,
    "Referencia": "salidaxventa",
    "Observaciones": "Venta"
  },
  {
    "MovimientoID": 5339,
    "ProductoID": 3,
    "Tipo": "SALIDA",
    "Cantidad": 1,
    "Fecha": "2026-01-17",
    "StockAntesMov": 116,
    "StockDespMov": 115,
    "CostoUnitario": 0.00,
    "Referencia": "salidaxventa",
    "Observaciones": "Venta"
  },
  {
    "MovimientoID": 5340,
    "ProductoID": 1,
    "Tipo": "SALIDA",
    "Cantidad": 4,
    "Fecha": "2026-01-17",
    "StockAntesMov": 779,
    "StockDespMov": 775,
    "CostoUnitario": 0.00,
    "Referencia": "salidaxventa",
    "Observaciones": "Venta"
  },
  {
    "MovimientoID": 5341,
    "ProductoID": 2,
    "Tipo": "SALIDA",
    "Cantidad": 3,
    "Fecha": "2026-01-17",
    "StockAntesMov": 69,
    "StockDespMov": 66,
    "CostoUnitario": 0.00,
    "Referencia": "salidaxventa",
    "Observaciones": "Venta"
  },
  {
    "MovimientoID": 5342,
    "ProductoID": 1,
    "Tipo": "SALIDA",
    "Cantidad": 2,
    "Fecha": "2026-01-17",
    "StockAntesMov": 775,
    "StockDespMov": 773,
    "CostoUnitario": 0.00,
    "Referencia": "salidaxventa",
    "Observaciones": "Venta"
  },
  {
    "MovimientoID": 5343,
    "ProductoID": 1,
    "Tipo": "SALIDA",
    "Cantidad": 1,
    "Fecha": "2026-01-17",
    "StockAntesMov": 773,
    "StockDespMov": 772,
    "CostoUnitario": 0.00,
    "Referencia": "salidaxventa",
    "Observaciones": "Venta"
  },
  {
    "MovimientoID": 5344,
    "ProductoID": 3,
    "Tipo": "SALIDA",
    "Cantidad": 1,
    "Fecha": "2026-01-17",
    "StockAntesMov": 115,
    "StockDespMov": 114,
    "CostoUnitario": 0.00,
    "Referencia": "salidaxventa",
    "Observaciones": "Venta"
  },
  {
    "MovimientoID": 5345,
    "ProductoID": 2,
    "Tipo": "SALIDA",
    "Cantidad": 1,
    "Fecha": "2026-01-17",
    "StockAntesMov": 66,
    "StockDespMov": 65,
    "CostoUnitario": 0.00,
    "Referencia": "salidaxventa",
    "Observaciones": "Venta"
  },
  {
    "MovimientoID": 5346,
    "ProductoID": 3,
    "Tipo": "SALIDA",
    "Cantidad": 23,
    "Fecha": "2026-01-17",
    "StockAntesMov": 114,
    "StockDespMov": 91,
    "CostoUnitario": 0.00,
    "Referencia": "salidaxventa",
    "Observaciones": "Venta"
  },
  {
    "MovimientoID": 5347,
    "ProductoID": 2,
    "Tipo": "SALIDA",
    "Cantidad": 1,
    "Fecha": "2026-01-19",
    "StockAntesMov": 65,
    "StockDespMov": 64,
    "CostoUnitario": 0.00,
    "Referencia": "salidaxventa",
    "Observaciones": "Venta"
  },
  {
    "MovimientoID": 5348,
    "ProductoID": 2,
    "Tipo": "SALIDA",
    "Cantidad": 1,
    "Fecha": "2026-01-19",
    "StockAntesMov": 64,
    "StockDespMov": 63,
    "CostoUnitario": 0.00,
    "Referencia": "salidaxventa",
    "Observaciones": "Venta"
  },
  {
    "MovimientoID": 5349,
    "ProductoID": 1,
    "Tipo": "SALIDA",
    "Cantidad": 1,
    "Fecha": "2026-01-19",
    "StockAntesMov": 772,
    "StockDespMov": 771,
    "CostoUnitario": 0.00,
    "Referencia": "salidaxventa",
    "Observaciones": "Venta"
  },
  {
    "MovimientoID": 5350,
    "ProductoID": 2,
    "Tipo": "SALIDA",
    "Cantidad": 1,
    "Fecha": "2026-01-19",
    "StockAntesMov": 63,
    "StockDespMov": 62,
    "CostoUnitario": 0.00,
    "Referencia": "salidaxventa",
    "Observaciones": "Venta"
  },
  {
    "MovimientoID": 5351,
    "ProductoID": 1,
    "Tipo": "SALIDA",
    "Cantidad": 3,
    "Fecha": "2026-01-19",
    "StockAntesMov": 771,
    "StockDespMov": 768,
    "CostoUnitario": 0.00,
    "Referencia": "salidaxventa",
    "Observaciones": "Venta"
  },
  {
    "MovimientoID": 5352,
    "ProductoID": 2,
    "Tipo": "SALIDA",
    "Cantidad": 1,
    "Fecha": "2026-01-19",
    "StockAntesMov": 62,
    "StockDespMov": 61,
    "CostoUnitario": 0.00,
    "Referencia": "salidaxventa",
    "Observaciones": "Venta"
  },
  {
    "MovimientoID": 5353,
    "ProductoID": 3,
    "Tipo": "SALIDA",
    "Cantidad": 10,
    "Fecha": "2026-01-19",
    "StockAntesMov": 91,
    "StockDespMov": 81,
    "CostoUnitario": 0.00,
    "Referencia": "salidaxventa",
    "Observaciones": "Venta"
  },
  {
    "MovimientoID": 5354,
    "ProductoID": 3,
    "Tipo": "SALIDA",
    "Cantidad": 1,
    "Fecha": "2026-01-19",
    "StockAntesMov": 81,
    "StockDespMov": 80,
    "CostoUnitario": 0.00,
    "Referencia": "salidaxventa",
    "Observaciones": "Venta"
  },
  {
    "MovimientoID": 5355,
    "ProductoID": 1,
    "Tipo": "SALIDA",
    "Cantidad": 1,
    "Fecha": "2026-01-19",
    "StockAntesMov": 768,
    "StockDespMov": 767,
    "CostoUnitario": 0.00,
    "Referencia": "salidaxventa",
    "Observaciones": "Venta"
  },
  {
    "MovimientoID": 5356,
    "ProductoID": 1,
    "Tipo": "SALIDA",
    "Cantidad": 1,
    "Fecha": "2026-01-20",
    "StockAntesMov": 767,
    "StockDespMov": 766,
    "CostoUnitario": 0.00,
    "Referencia": "salidaxventa",
    "Observaciones": "Venta"
  },
  {
    "MovimientoID": 5357,
    "ProductoID": 2,
    "Tipo": "SALIDA",
    "Cantidad": 1,
    "Fecha": "2026-01-20",
    "StockAntesMov": 61,
    "StockDespMov": 60,
    "CostoUnitario": 0.00,
    "Referencia": "salidaxventa",
    "Observaciones": "Venta"
  },
  {
    "MovimientoID": 5358,
    "ProductoID": 1,
    "Tipo": "SALIDA",
    "Cantidad": 1,
    "Fecha": "2026-01-20",
    "StockAntesMov": 766,
    "StockDespMov": 765,
    "CostoUnitario": 0.00,
    "Referencia": "salidaxventa",
    "Observaciones": "Venta"
  },
  {
    "MovimientoID": 5359,
    "ProductoID": 1,
    "Tipo": "SALIDA",
    "Cantidad": 4,
    "Fecha": "2026-01-20",
    "StockAntesMov": 765,
    "StockDespMov": 761,
    "CostoUnitario": 0.00,
    "Referencia": "salidaxventa",
    "Observaciones": "Venta"
  },
  {
    "MovimientoID": 5360,
    "ProductoID": 2,
    "Tipo": "SALIDA",
    "Cantidad": 1,
    "Fecha": "2026-01-21",
    "StockAntesMov": 60,
    "StockDespMov": 59,
    "CostoUnitario": 0.00,
    "Referencia": "salidaxventa",
    "Observaciones": "Venta"
  },
  {
    "MovimientoID": 5361,
    "ProductoID": 1,
    "Tipo": "SALIDA",
    "Cantidad": 1,
    "Fecha": "2026-01-21",
    "StockAntesMov": 761,
    "StockDespMov": 760,
    "CostoUnitario": 0.00,
    "Referencia": "salidaxventa",
    "Observaciones": "Venta"
  },
  {
    "MovimientoID": 5362,
    "ProductoID": 1,
    "Tipo": "SALIDA",
    "Cantidad": 3,
    "Fecha": "2026-01-21",
    "StockAntesMov": 760,
    "StockDespMov": 757,
    "CostoUnitario": 0.00,
    "Referencia": "salidaxventa",
    "Observaciones": "Venta"
  },
  {
    "MovimientoID": 5363,
    "ProductoID": 1,
    "Tipo": "SALIDA",
    "Cantidad": 1,
    "Fecha": "2026-01-21",
    "StockAntesMov": 757,
    "StockDespMov": 756,
    "CostoUnitario": 0.00,
    "Referencia": "salidaxventa",
    "Observaciones": "Venta"
  },
  {
    "MovimientoID": 5364,
    "ProductoID": 1,
    "Tipo": "SALIDA",
    "Cantidad": 1,
    "Fecha": "2026-01-21",
    "StockAntesMov": 756,
    "StockDespMov": 755,
    "CostoUnitario": 0.00,
    "Referencia": "salidaxventa",
    "Observaciones": "Venta"
  },
  {
    "MovimientoID": 5365,
    "ProductoID": 2,
    "Tipo": "SALIDA",
    "Cantidad": 1,
    "Fecha": "2026-01-21",
    "StockAntesMov": 59,
    "StockDespMov": 58,
    "CostoUnitario": 0.00,
    "Referencia": "salidaxventa",
    "Observaciones": "Venta"
  },
  {
    "MovimientoID": 5366,
    "ProductoID": 2,
    "Tipo": "SALIDA",
    "Cantidad": 10,
    "Fecha": "2026-01-21",
    "StockAntesMov": 58,
    "StockDespMov": 48,
    "CostoUnitario": 0.00,
    "Referencia": "salidaxventa",
    "Observaciones": "Venta"
  },
  {
    "MovimientoID": 5367,
    "ProductoID": 1,
    "Tipo": "SALIDA",
    "Cantidad": 10,
    "Fecha": "2026-01-21",
    "StockAntesMov": 755,
    "StockDespMov": 745,
    "CostoUnitario": 0.00,
    "Referencia": "salidaxventa",
    "Observaciones": "Venta"
  },
  {
    "MovimientoID": 5368,
    "ProductoID": 2,
    "Tipo": "SALIDA",
    "Cantidad": 10,
    "Fecha": "2026-01-21",
    "StockAntesMov": 48,
    "StockDespMov": 38,
    "CostoUnitario": 0.00,
    "Referencia": "salidaxventa",
    "Observaciones": "Venta"
  },
  {
    "MovimientoID": 5369,
    "ProductoID": 1,
    "Tipo": "SALIDA",
    "Cantidad": 1,
    "Fecha": "2026-01-21",
    "StockAntesMov": 745,
    "StockDespMov": 744,
    "CostoUnitario": 0.00,
    "Referencia": "salidaxventa",
    "Observaciones": "Venta"
  },
  {
    "MovimientoID": 5370,
    "ProductoID": 1,
    "Tipo": "SALIDA",
    "Cantidad": 1,
    "Fecha": "2026-01-21",
    "StockAntesMov": 744,
    "StockDespMov": 743,
    "CostoUnitario": 0.00,
    "Referencia": "salidaxventa",
    "Observaciones": "Venta"
  },
  {
    "MovimientoID": 5371,
    "ProductoID": 1,
    "Tipo": "SALIDA",
    "Cantidad": 1,
    "Fecha": "2026-01-21",
    "StockAntesMov": 743,
    "StockDespMov": 742,
    "CostoUnitario": 0.00,
    "Referencia": "salidaxventa",
    "Observaciones": "Venta"
  },
  {
    "MovimientoID": 5372,
    "ProductoID": 1,
    "Tipo": "SALIDA",
    "Cantidad": 2,
    "Fecha": "2026-01-21",
    "StockAntesMov": 742,
    "StockDespMov": 740,
    "CostoUnitario": 0.00,
    "Referencia": "salidaxventa",
    "Observaciones": "Venta"
  },
  {
    "MovimientoID": 5373,
    "ProductoID": 1,
    "Tipo": "SALIDA",
    "Cantidad": 2,
    "Fecha": "2026-01-21",
    "StockAntesMov": 740,
    "StockDespMov": 738,
    "CostoUnitario": 0.00,
    "Referencia": "salidaxventa",
    "Observaciones": "Venta"
  },
  {
    "MovimientoID": 5374,
    "ProductoID": 2,
    "Tipo": "SALIDA",
    "Cantidad": 2,
    "Fecha": "2026-01-21",
    "StockAntesMov": 38,
    "StockDespMov": 36,
    "CostoUnitario": 0.00,
    "Referencia": "salidaxventa",
    "Observaciones": "Venta"
  },
  {
    "MovimientoID": 5375,
    "ProductoID": 1,
    "Tipo": "SALIDA",
    "Cantidad": 1,
    "Fecha": "2026-01-21",
    "StockAntesMov": 738,
    "StockDespMov": 737,
    "CostoUnitario": 0.00,
    "Referencia": "salidaxventa",
    "Observaciones": "Venta"
  },
  {
    "MovimientoID": 5376,
    "ProductoID": 1,
    "Tipo": "SALIDA",
    "Cantidad": 1,
    "Fecha": "2026-01-22",
    "StockAntesMov": 737,
    "StockDespMov": 736,
    "CostoUnitario": 0.00,
    "Referencia": "salidaxventa",
    "Observaciones": "Venta"
  },
  {
    "MovimientoID": 5377,
    "ProductoID": 2,
    "Tipo": "SALIDA",
    "Cantidad": 1,
    "Fecha": "2026-01-22",
    "StockAntesMov": 36,
    "StockDespMov": 35,
    "CostoUnitario": 0.00,
    "Referencia": "salidaxventa",
    "Observaciones": "Venta"
  },
  {
    "MovimientoID": 5378,
    "ProductoID": 1,
    "Tipo": "SALIDA",
    "Cantidad": 1,
    "Fecha": "2026-01-22",
    "StockAntesMov": 736,
    "StockDespMov": 735,
    "CostoUnitario": 0.00,
    "Referencia": "salidaxventa",
    "Observaciones": "Venta"
  },
  {
    "MovimientoID": 5379,
    "ProductoID": 1,
    "Tipo": "SALIDA",
    "Cantidad": 1,
    "Fecha": "2026-01-22",
    "StockAntesMov": 735,
    "StockDespMov": 734,
    "CostoUnitario": 0.00,
    "Referencia": "salidaxventa",
    "Observaciones": "Venta"
  },
  {
    "MovimientoID": 5380,
    "ProductoID": 3,
    "Tipo": "SALIDA",
    "Cantidad": 1,
    "Fecha": "2026-01-22",
    "StockAntesMov": 80,
    "StockDespMov": 79,
    "CostoUnitario": 0.00,
    "Referencia": "salidaxventa",
    "Observaciones": "Venta"
  },
  {
    "MovimientoID": 5381,
    "ProductoID": 2,
    "Tipo": "SALIDA",
    "Cantidad": 1,
    "Fecha": "2026-01-22",
    "StockAntesMov": 35,
    "StockDespMov": 34,
    "CostoUnitario": 0.00,
    "Referencia": "salidaxventa",
    "Observaciones": "Venta"
  },
  {
    "MovimientoID": 5382,
    "ProductoID": 2,
    "Tipo": "SALIDA",
    "Cantidad": 1,
    "Fecha": "2026-01-22",
    "StockAntesMov": 34,
    "StockDespMov": 33,
    "CostoUnitario": 0.00,
    "Referencia": "salidaxventa",
    "Observaciones": "Venta"
  },
  {
    "MovimientoID": 5383,
    "ProductoID": 1,
    "Tipo": "SALIDA",
    "Cantidad": 1,
    "Fecha": "2026-01-22",
    "StockAntesMov": 734,
    "StockDespMov": 733,
    "CostoUnitario": 0.00,
    "Referencia": "salidaxventa",
    "Observaciones": "Venta"
  },
  {
    "MovimientoID": 5384,
    "ProductoID": 3,
    "Tipo": "SALIDA",
    "Cantidad": 12,
    "Fecha": "2026-01-22",
    "StockAntesMov": 79,
    "StockDespMov": 67,
    "CostoUnitario": 0.00,
    "Referencia": "salidaxventa",
    "Observaciones": "Venta"
  },
  {
    "MovimientoID": 5385,
    "ProductoID": 3,
    "Tipo": "SALIDA",
    "Cantidad": 14,
    "Fecha": "2026-01-22",
    "StockAntesMov": 67,
    "StockDespMov": 53,
    "CostoUnitario": 0.00,
    "Referencia": "salidaxventa",
    "Observaciones": "Venta"
  },
  {
    "MovimientoID": 5386,
    "ProductoID": 1,
    "Tipo": "SALIDA",
    "Cantidad": 1,
    "Fecha": "2026-01-23",
    "StockAntesMov": 733,
    "StockDespMov": 732,
    "CostoUnitario": 0.00,
    "Referencia": "salidaxventa",
    "Observaciones": "Venta"
  },
  {
    "MovimientoID": 5387,
    "ProductoID": 1,
    "Tipo": "SALIDA",
    "Cantidad": 3,
    "Fecha": "2026-01-23",
    "StockAntesMov": 732,
    "StockDespMov": 729,
    "CostoUnitario": 0.00,
    "Referencia": "salidaxventa",
    "Observaciones": "Venta"
  },
  {
    "MovimientoID": 5388,
    "ProductoID": 1,
    "Tipo": "SALIDA",
    "Cantidad": 3,
    "Fecha": "2026-01-23",
    "StockAntesMov": 729,
    "StockDespMov": 726,
    "CostoUnitario": 0.00,
    "Referencia": "salidaxventa",
    "Observaciones": "Venta"
  },
  {
    "MovimientoID": 5389,
    "ProductoID": 1,
    "Tipo": "SALIDA",
    "Cantidad": 2,
    "Fecha": "2026-01-23",
    "StockAntesMov": 726,
    "StockDespMov": 724,
    "CostoUnitario": 0.00,
    "Referencia": "salidaxventa",
    "Observaciones": "Venta"
  },
  {
    "MovimientoID": 5390,
    "ProductoID": 2,
    "Tipo": "SALIDA",
    "Cantidad": 2,
    "Fecha": "2026-01-23",
    "StockAntesMov": 33,
    "StockDespMov": 31,
    "CostoUnitario": 0.00,
    "Referencia": "salidaxventa",
    "Observaciones": "Venta"
  },
  {
    "MovimientoID": 5391,
    "ProductoID": 1,
    "Tipo": "SALIDA",
    "Cantidad": 2,
    "Fecha": "2026-01-23",
    "StockAntesMov": 724,
    "StockDespMov": 722,
    "CostoUnitario": 0.00,
    "Referencia": "salidaxventa",
    "Observaciones": "Venta"
  },
  {
    "MovimientoID": 5392,
    "ProductoID": 1,
    "Tipo": "SALIDA",
    "Cantidad": 1,
    "Fecha": "2026-01-23",
    "StockAntesMov": 722,
    "StockDespMov": 721,
    "CostoUnitario": 0.00,
    "Referencia": "salidaxventa",
    "Observaciones": "Venta"
  },
  {
    "MovimientoID": 5393,
    "ProductoID": 3,
    "Tipo": "SALIDA",
    "Cantidad": 15,
    "Fecha": "2026-01-23",
    "StockAntesMov": 53,
    "StockDespMov": 38,
    "CostoUnitario": 0.00,
    "Referencia": "salidaxventa",
    "Observaciones": "Venta"
  },
  {
    "MovimientoID": 5394,
    "ProductoID": 2,
    "Tipo": "SALIDA",
    "Cantidad": 1,
    "Fecha": "2026-01-23",
    "StockAntesMov": 31,
    "StockDespMov": 30,
    "CostoUnitario": 0.00,
    "Referencia": "salidaxventa",
    "Observaciones": "Venta"
  },
  {
    "MovimientoID": 5395,
    "ProductoID": 1,
    "Tipo": "SALIDA",
    "Cantidad": 2,
    "Fecha": "2026-01-23",
    "StockAntesMov": 721,
    "StockDespMov": 719,
    "CostoUnitario": 0.00,
    "Referencia": "salidaxventa",
    "Observaciones": "Venta"
  },
  {
    "MovimientoID": 5396,
    "ProductoID": 1,
    "Tipo": "SALIDA",
    "Cantidad": 3,
    "Fecha": "2026-01-26",
    "StockAntesMov": 719,
    "StockDespMov": 716,
    "CostoUnitario": 0.00,
    "Referencia": "salidaxventa",
    "Observaciones": "Venta"
  },
  {
    "MovimientoID": 5397,
    "ProductoID": 2,
    "Tipo": "SALIDA",
    "Cantidad": 1,
    "Fecha": "2026-01-26",
    "StockAntesMov": 30,
    "StockDespMov": 29,
    "CostoUnitario": 0.00,
    "Referencia": "salidaxventa",
    "Observaciones": "Venta"
  },
  {
    "MovimientoID": 5398,
    "ProductoID": 1,
    "Tipo": "SALIDA",
    "Cantidad": 1,
    "Fecha": "2026-01-26",
    "StockAntesMov": 716,
    "StockDespMov": 715,
    "CostoUnitario": 0.00,
    "Referencia": "salidaxventa",
    "Observaciones": "Venta"
  },
  {
    "MovimientoID": 5399,
    "ProductoID": 1,
    "Tipo": "SALIDA",
    "Cantidad": 4,
    "Fecha": "2026-01-26",
    "StockAntesMov": 715,
    "StockDespMov": 711,
    "CostoUnitario": 0.00,
    "Referencia": "salidaxventa",
    "Observaciones": "Venta"
  },
  {
    "MovimientoID": 5400,
    "ProductoID": 2,
    "Tipo": "SALIDA",
    "Cantidad": 1,
    "Fecha": "2026-01-26",
    "StockAntesMov": 29,
    "StockDespMov": 28,
    "CostoUnitario": 0.00,
    "Referencia": "salidaxventa",
    "Observaciones": "Venta"
  },
  {
    "MovimientoID": 5401,
    "ProductoID": 2,
    "Tipo": "SALIDA",
    "Cantidad": 1,
    "Fecha": "2026-01-26",
    "StockAntesMov": 28,
    "StockDespMov": 27,
    "CostoUnitario": 0.00,
    "Referencia": "salidaxventa",
    "Observaciones": "Venta"
  },
  {
    "MovimientoID": 5402,
    "ProductoID": 3,
    "Tipo": "SALIDA",
    "Cantidad": 6,
    "Fecha": "2026-01-26",
    "StockAntesMov": 38,
    "StockDespMov": 32,
    "CostoUnitario": 0.00,
    "Referencia": "salidaxventa",
    "Observaciones": "Venta"
  },
  {
    "MovimientoID": 5403,
    "ProductoID": 1,
    "Tipo": "SALIDA",
    "Cantidad": 1,
    "Fecha": "2026-01-26",
    "StockAntesMov": 711,
    "StockDespMov": 710,
    "CostoUnitario": 0.00,
    "Referencia": "salidaxventa",
    "Observaciones": "Venta"
  },
  {
    "MovimientoID": 5404,
    "ProductoID": 1,
    "Tipo": "SALIDA",
    "Cantidad": 1,
    "Fecha": "2026-01-26",
    "StockAntesMov": 710,
    "StockDespMov": 709,
    "CostoUnitario": 0.00,
    "Referencia": "salidaxventa",
    "Observaciones": "Venta"
  },
  {
    "MovimientoID": 5405,
    "ProductoID": 1,
    "Tipo": "SALIDA",
    "Cantidad": 1,
    "Fecha": "2026-01-27",
    "StockAntesMov": 709,
    "StockDespMov": 708,
    "CostoUnitario": 0.00,
    "Referencia": "salidaxventa",
    "Observaciones": "Venta"
  },
  {
    "MovimientoID": 5406,
    "ProductoID": 1,
    "Tipo": "SALIDA",
    "Cantidad": 1,
    "Fecha": "2026-01-27",
    "StockAntesMov": 708,
    "StockDespMov": 707,
    "CostoUnitario": 0.00,
    "Referencia": "salidaxventa",
    "Observaciones": "Venta"
  },
  {
    "MovimientoID": 5407,
    "ProductoID": 1,
    "Tipo": "SALIDA",
    "Cantidad": 3,
    "Fecha": "2026-01-27",
    "StockAntesMov": 707,
    "StockDespMov": 704,
    "CostoUnitario": 0.00,
    "Referencia": "salidaxventa",
    "Observaciones": "Venta"
  },
  {
    "MovimientoID": 5408,
    "ProductoID": 2,
    "Tipo": "SALIDA",
    "Cantidad": 1,
    "Fecha": "2026-01-27",
    "StockAntesMov": 27,
    "StockDespMov": 26,
    "CostoUnitario": 0.00,
    "Referencia": "salidaxventa",
    "Observaciones": "Venta"
  },
  {
    "MovimientoID": 5409,
    "ProductoID": 1,
    "Tipo": "SALIDA",
    "Cantidad": 2,
    "Fecha": "2026-01-27",
    "StockAntesMov": 704,
    "StockDespMov": 702,
    "CostoUnitario": 0.00,
    "Referencia": "salidaxventa",
    "Observaciones": "Venta"
  }
]