[
  {
    "Folio": "VM-701",
    "Fecha": "2026-07-01",
    "Hora": "00:00:00",
    "Cliente": "Publico",
    "TipoDeCompra": "Vending",
    "TipoDePago": "Monedero",
    "Subtotal": 6.00,
    "Iva": 0.00,
    "Total": 6.00,
    "Efectivo": 6.00,
    "Tarjeta": 0.00,
    "Transferencia": 0.00,
    "Usuario": "ESP32"
  },
  {
    "Folio": "VM-702",
    "Fecha": "2026-07-01",
    "Hora": "00:00:00",
    "Cliente": "Publico",
    "TipoDeCompra": "Vending",
    "TipoDePago": "Monedero",
    "Subtotal": 4.00,
    "Iva": 0.00,
    "Total": 4.00,
    "Efectivo": 4.00,
    "Tarjeta": 0.00,
    "Transferencia": 0.00,
    "Usuario": "ESP32"
  },
  {
    "Folio": "VM-703",
    "Fecha": "2026-07-01",
    "Hora": "00:00:00",
    "Cliente": "Publico",
    "TipoDeCompra": "Vending",
    "TipoDePago": "Monedero",
    "Subtotal": 5.00,
    "Iva": 0.00,
    "Total": 5.00,
    "Efectivo": 5.00,
    "Tarjeta": 0.00,
    "Transferencia": 0.00,
    "Usuario": "ESP32"
  },
  {
    "Folio": "VM-704",
    "Fecha": "2026-07-01",
    "Hora": "00:00:00",
    "Cliente": "Publico",
    "TipoDeCompra": "Vending",
    "TipoDePago": "Monedero",
    "Subtotal": 5.00,
    "Iva": 0.00,
    "Total": 5.00,
    "Efectivo": 5.00,
    "Tarjeta": 0.00,
    "Transferencia": 0.00,
    "Usuario": "ESP32"
  },
  {
    "Folio": "VM-705",
    "Fecha": "2026-07-01",
    "Hora": "00:00:00",
    "Cliente": "Publico",
    "TipoDeCompra": "Vending",
    "TipoDePago": "Monedero",
    "Subtotal": 10.00,
    "Iva": 0.00,
    "Total": 10.00,
    "Efectivo": 10.00,
    "Tarjeta": 0.00,
    "Transferencia": 0.00,
    "Usuario": "ESP32"
  },
  {
    "Folio": "VM-706",
    "Fecha": "2026-07-01",
    "Hora": "00:00:00",
    "Cliente": "Publico",
    "TipoDeCompra": "Vending",
    "TipoDePago": "Monedero",
    "Subtotal": 10.00,
    "Iva": 0.00,
    "Total": 10.00,
    "Efectivo": 10.00,
    "Tarjeta": 0.00,
    "Transferencia": 0.00,
    "Usuario": "ESP32"
  },
  {
    "Folio": "VM-707",
    "Fecha": "2026-07-01",
    "Hora": "00:00:00",
    "Cliente": "Publico",
    "TipoDeCompra": "Vending",
    "TipoDePago": "Monedero",
    "Subtotal": 5.00,
    "Iva": 0.00,
    "Total": 5.00,
    "Efectivo": 5.00,
    "Tarjeta": 0.00,
    "Transferencia": 0.00,
    "Usuario": "ESP32"
  },
  {
    "Folio": "VM-708",
    "Fecha": "2026-07-01",
    "Hora": "00:00:00",
    "Cliente": "Publico",
    "TipoDeCompra": "Vending",
    "TipoDePago": "Monedero",
    "Subtotal": 10.00,
    "Iva": 0.00,
    "Total": 10.00,
    "Efectivo": 10.00,
    "Tarjeta": 0.00,
    "Transferencia": 0.00,
    "Usuario": "ESP32"
  },
  {
    "Folio": "VM-709",
    "Fecha": "2026-07-01",
    "Hora": "00:00:00",
    "Cliente": "Publico",
    "TipoDeCompra": "Vending",
    "TipoDePago": "Monedero",
    "Subtotal": 4.00,
    "Iva": 0.00,
    "Total": 4.00,
    "Efectivo": 4.00,
    "Tarjeta": 0.00,
    "Transferencia": 0.00,
    "Usuario": "ESP32"
  },
  {
    "Folio": "VM-710",
    "Fecha": "2026-07-01",
    "Hora": "00:00:00",
    "Cliente": "Publico",
    "TipoDeCompra": "Vending",
    "TipoDePago": "Monedero",
    "Subtotal": 5.00,
    "Iva": 0.00,
    "Total": 5.00,
    "Efectivo": 5.00,
    "Tarjeta": 0.00,
    "Transferencia": 0.00,
    "Usuario": "ESP32"
  },
  {
    "Folio": "VM-711",
    "Fecha": "2026-07-01",
    "Hora": "00:00:00",
    "Cliente": "Publico",
    "TipoDeCompra": "Vending",
    "TipoDePago": "Monedero",
    "Subtotal": 1.00,
    "Iva": 0.00,
    "Total": 1.00,
    "Efectivo": 1.00,
    "Tarjeta": 0.00,
    "Transferencia": 0.00,
    "Usuario": "ESP32"
  },
  {
    "Folio": "VM-712",
    "Fecha": "2026-07-01",
    "Hora": "00:00:00",
    "Cliente": "Publico",
    "TipoDeCompra": "Vending",
    "TipoDePago": "Monedero",
    "Subtotal": 12.00,
    "Iva": 0.00,
    "Total": 12.00,
    "Efectivo": 12.00,
    "Tarjeta": 0.00,
    "Transferencia": 0.00,
    "Usuario": "ESP32"
  },
  {
    "Folio": "VMEN-2258",
    "Fecha": "2026-07-01",
    "Hora": "09:34:36",
    "Cliente": "N/A",
    "TipoDeCompra": "Menudeo",
    "TipoDePago": "Efectivo",
    "Subtotal": 40.00,
    "Iva": 0.00,
    "Total": 40.00,
    "Efectivo": 40.00,
    "Tarjeta": 0.00,
    "Transferencia": 0.00,
    "Usuario": "ramon gracia"
  },
  {
    "Folio": "VMEN-2259",
    "Fecha": "2026-07-01",
    "Hora": "09:35:47",
    "Cliente": "N/A",
    "TipoDeCompra": "Menudeo",
    "TipoDePago": "Efectivo",
    "Subtotal": 10.00,
    "Iva": 0.00,
    "Total": 10.00,
    "Efectivo": 10.00,
    "Tarjeta": 0.00,
    "Transferencia": 0.00,
    "Usuario": "ramon gracia"
  },
  {
    "Folio": "VMEN-2260",
    "Fecha": "2026-07-01",
    "Hora": "09:48:16",
    "Cliente": "N/A",
    "TipoDeCompra": "Menudeo",
    "TipoDePago": "Tarjeta",
    "Subtotal": 100.00,
    "Iva": 0.00,
    "Total": 100.00,
    "Efectivo": 0.00,
    "Tarjeta": 100.00,
    "Transferencia": 0.00,
    "Usuario": "ramon gracia"
  },
  {
    "Folio": "VMEN-2261",
    "Fecha": "2026-07-01",
    "Hora": "10:17:25",
    "Cliente": "N/A",
    "TipoDeCompra": "Menudeo",
    "TipoDePago": "Tarjeta",
    "Subtotal": 40.00,
    "Iva": 0.00,
    "Total": 40.00,
    "Efectivo": 0.00,
    "Tarjeta": 40.00,
    "Transferencia": 0.00,
    "Usuario": "ramon gracia"
  },
  {
    "Folio": "VMEN-2262",
    "Fecha": "2026-07-01",
    "Hora": "10:24:53",
    "Cliente": "N/A",
    "TipoDeCompra": "Menudeo",
    "TipoDePago": "Efectivo",
    "Subtotal": 50.00,
    "Iva": 0.00,
    "Total": 50.00,
    "Efectivo": 50.00,
    "Tarjeta": 0.00,
    "Transferencia": 0.00,
    "Usuario": "ramon gracia"
  },
  {
    "Folio": "VMEN-2263",
    "Fecha": "2026-07-01",
    "Hora": "10:41:08",
    "Cliente": "N/A",
    "TipoDeCompra": "Menudeo",
    "TipoDePago": "Efectivo",
    "Subtotal": 10.00,
    "Iva": 0.00,
    "Total": 10.00,
    "Efectivo": 10.00,
    "Tarjeta": 0.00,
    "Transferencia": 0.00,
    "Usuario": "ramon gracia"
  },
  {
    "Folio": "VM-713",
    "Fecha": "2026-07-01",
    "Hora": "00:00:00",
    "Cliente": "Publico",
    "TipoDeCompra": "Vending",
    "TipoDePago": "Monedero",
    "Subtotal": 10.00,
    "Iva": 0.00,
    "Total": 10.00,
    "Efectivo": 10.00,
    "Tarjeta": 0.00,
    "Transferencia": 0.00,
    "Usuario": "ESP32"
  },
  {
    "Folio": "VM-714",
    "Fecha": "2026-07-01",
    "Hora": "00:00:00",
    "Cliente": "Publico",
    "TipoDeCompra": "Vending",
    "TipoDePago": "Monedero",
    "Subtotal": 10.00,
    "Iva": 0.00,
    "Total": 10.00,
    "Efectivo": 10.00,
    "Tarjeta": 0.00,
    "Transferencia": 0.00,
    "Usuario": "ESP32"
  },
  {
    "Folio": "VM-715",
    "Fecha": "2026-07-01",
    "Hora": "00:00:00",
    "Cliente": "Publico",
    "TipoDeCompra": "Vending",
    "TipoDePago": "Monedero",
    "Subtotal": 10.00,
    "Iva": 0.00,
    "Total": 10.00,
    "Efectivo": 10.00,
    "Tarjeta": 0.00,
    "Transferencia": 0.00,
    "Usuario": "ESP32"
  },
  {
    "Folio": "VM-716",
    "Fecha": "2026-07-01",
    "Hora": "00:00:00",
    "Cliente": "Publico",
    "TipoDeCompra": "Vending",
    "TipoDePago": "Monedero",
    "Subtotal": 10.00,
    "Iva": 0.00,
    "Total": 10.00,
    "Efectivo": 10.00,
    "Tarjeta": 0.00,
    "Transferencia": 0.00,
    "Usuario": "ESP32"
  },
  {
    "Folio": "VM-717",
    "Fecha": "2026-07-01",
    "Hora": "00:00:00",
    "Cliente": "Publico",
    "TipoDeCompra": "Vending",
    "TipoDePago": "Monedero",
    "Subtotal": 5.00,
    "Iva": 0.00,
    "Total": 5.00,
    "Efectivo": 5.00,
    "Tarjeta": 0.00,
    "Transferencia": 0.00,
    "Usuario": "ESP32"
  },
  {
    "Folio": "VM-718",
    "Fecha": "2026-07-01",
    "Hora": "00:00:00",
    "Cliente": "Publico",
    "TipoDeCompra": "Vending",
    "TipoDePago": "Monedero",
    "Subtotal": 5.00,
    "Iva": 0.00,
    "Total": 5.00,
    "Efectivo": 5.00,
    "Tarjeta": 0.00,
    "Transferencia": 0.00,
    "Usuario": "ESP32"
  },
  {
    "Folio": "VM-719",
    "Fecha": "2026-07-01",
    "Hora": "00:00:00",
    "Cliente": "Publico",
    "TipoDeCompra": "Vending",
    "TipoDePago": "Monedero",
    "Subtotal": 1.00,
    "Iva": 0.00,
    "Total": 1.00,
    "Efectivo": 1.00,
    "Tarjeta": 0.00,
    "Transferencia": 0.00,
    "Usuario": "ESP32"
  },
  {
    "Folio": "VMEN-2264",
    "Fecha": "2026-07-01",
    "Hora": "11:34:19",
    "Cliente": "N/A",
    "TipoDeCompra": "Menudeo",
    "TipoDePago": "Efectivo",
    "Subtotal": 35.00,
    "Iva": 0.00,
    "Total": 35.00,
    "Efectivo": 35.00,
    "Tarjeta": 0.00,
    "Transferencia": 0.00,
    "Usuario": "ramon gracia"
  },
  {
    "Folio": "VMEN-2265",
    "Fecha": "2026-07-01",
    "Hora": "11:46:30",
    "Cliente": "N/A",
    "TipoDeCompra": "Menudeo",
    "TipoDePago": "Efectivo",
    "Subtotal": 45.00,
    "Iva": 0.00,
    "Total": 45.00,
    "Efectivo": 45.00,
    "Tarjeta": 0.00,
    "Transferencia": 0.00,
    "Usuario": "ramon gracia"
  },
  {
    "Folio": "VMEN-2266",
    "Fecha": "2026-07-01",
    "Hora": "12:06:11",
    "Cliente": "N/A",
    "TipoDeCompra": "Menudeo",
    "TipoDePago": "Efectivo",
    "Subtotal": 15.00,
    "Iva": 0.00,
    "Total": 15.00,
    "Efectivo": 15.00,
    "Tarjeta": 0.00,
    "Transferencia": 0.00,
    "Usuario": "ramon gracia"
  },
  {
    "Folio": "VMEN-2267",
    "Fecha": "2026-07-01",
    "Hora": "12:53:33",
    "Cliente": "N/A",
    "TipoDeCompra": "Menudeo",
    "TipoDePago": "Efectivo",
    "Subtotal": 50.00,
    "Iva": 0.00,
    "Total": 50.00,
    "Efectivo": 50.00,
    "Tarjeta": 0.00,
    "Transferencia": 0.00,
    "Usuario": "Gabriela Gracia"
  },
  {
    "Folio": "VMEN-2268",
    "Fecha": "2026-07-01",
    "Hora": "13:00:01",
    "Cliente": "N/A",
    "TipoDeCompra": "Menudeo",
    "TipoDePago": "Tarjeta",
    "Subtotal": 40.00,
    "Iva": 0.00,
    "Total": 40.00,
    "Efectivo": 0.00,
    "Tarjeta": 40.00,
    "Transferencia": 0.00,
    "Usuario": "Gabriela Gracia"
  },
  {
    "Folio": "VMEN-2269",
    "Fecha": "2026-07-01",
    "Hora": "13:34:37",
    "Cliente": "N/A",
    "TipoDeCompra": "Menudeo",
    "TipoDePago": "Efectivo",
    "Subtotal": 20.00,
    "Iva": 0.00,
    "Total": 20.00,
    "Efectivo": 20.00,
    "Tarjeta": 0.00,
    "Transferencia": 0.00,
    "Usuario": "Gabriela Gracia"
  },
  {
    "Folio": "VM-720",
    "Fecha": "2026-07-01",
    "Hora": "00:00:00",
    "Cliente": "Publico",
    "TipoDeCompra": "Vending",
    "TipoDePago": "Monedero",
    "Subtotal": 1.00,
    "Iva": 0.00,
    "Total": 1.00,
    "Efectivo": 1.00,
    "Tarjeta": 0.00,
    "Transferencia": 0.00,
    "Usuario": "ESP32"
  },
  {
    "Folio": "VM-721",
    "Fecha": "2026-07-01",
    "Hora": "00:00:00",
    "Cliente": "Publico",
    "TipoDeCompra": "Vending",
    "TipoDePago": "Monedero",
    "Subtotal": 1.00,
    "Iva": 0.00,
    "Total": 1.00,
    "Efectivo": 1.00,
    "Tarjeta": 0.00,
    "Transferencia": 0.00,
    "Usuario": "ESP32"
  },
  {
    "Folio": "VM-722",
    "Fecha": "2026-07-01",
    "Hora": "00:00:00",
    "Cliente": "Publico",
    "TipoDeCompra": "Vending",
    "TipoDePago": "Monedero",
    "Subtotal": 1.00,
    "Iva": 0.00,
    "Total": 1.00,
    "Efectivo": 1.00,
    "Tarjeta": 0.00,
    "Transferencia": 0.00,
    "Usuario": "ESP32"
  },
  {
    "Folio": "VM-723",
    "Fecha": "2026-07-01",
    "Hora": "00:00:00",
    "Cliente": "Publico",
    "TipoDeCompra": "Vending",
    "TipoDePago": "Monedero",
    "Subtotal": 1.00,
    "Iva": 0.00,
    "Total": 1.00,
    "Efectivo": 1.00,
    "Tarjeta": 0.00,
    "Transferencia": 0.00,
    "Usuario": "ESP32"
  },
  {
    "Folio": "VM-724",
    "Fecha": "2026-07-01",
    "Hora": "00:00:00",
    "Cliente": "Publico",
    "TipoDeCompra": "Vending",
    "TipoDePago": "Monedero",
    "Subtotal": 1.00,
    "Iva": 0.00,
    "Total": 1.00,
    "Efectivo": 1.00,
    "Tarjeta": 0.00,
    "Transferencia": 0.00,
    "Usuario": "ESP32"
  },
  {
    "Folio": "VM-725",
    "Fecha": "2026-07-01",
    "Hora": "00:00:00",
    "Cliente": "Publico",
    "TipoDeCompra": "Vending",
    "TipoDePago": "Monedero",
    "Subtotal": 1.00,
    "Iva": 0.00,
    "Total": 1.00,
    "Efectivo": 1.00,
    "Tarjeta": 0.00,
    "Transferencia": 0.00,
    "Usuario": "ESP32"
  },
  {
    "Folio": "VM-726",
    "Fecha": "2026-07-01",
    "Hora": "00:00:00",
    "Cliente": "Publico",
    "TipoDeCompra": "Vending",
    "TipoDePago": "Monedero",
    "Subtotal": 1.00,
    "Iva": 0.00,
    "Total": 1.00,
    "Efectivo": 1.00,
    "Tarjeta": 0.00,
    "Transferencia": 0.00,
    "Usuario": "ESP32"
  },
  {
    "Folio": "VM-727",
    "Fecha": "2026-07-01",
    "Hora": "00:00:00",
    "Cliente": "Publico",
    "TipoDeCompra": "Vending",
    "TipoDePago": "Monedero",
    "Subtotal": 8.00,
    "Iva": 0.00,
    "Total": 8.00,
    "Efectivo": 8.00,
    "Tarjeta": 0.00,
    "Transferencia": 0.00,
    "Usuario": "ESP32"
  },
  {
    "Folio": "VM-728",
    "Fecha": "2026-07-01",
    "Hora": "00:00:00",
    "Cliente": "Publico",
    "TipoDeCompra": "Vending",
    "TipoDePago": "Monedero",
    "Subtotal": 8.00,
    "Iva": 0.00,
    "Total": 8.00,
    "Efectivo": 8.00,
    "Tarjeta": 0.00,
    "Transferencia": 0.00,
    "Usuario": "ESP32"
  },
  {
    "Folio": "VM-729",
    "Fecha": "2026-07-01",
    "Hora": "00:00:00",
    "Cliente": "Publico",
    "TipoDeCompra": "Vending",
    "TipoDePago": "Monedero",
    "Subtotal": 8.00,
    "Iva": 0.00,
    "Total": 8.00,
    "Efectivo": 8.00,
    "Tarjeta": 0.00,
    "Transferencia": 0.00,
    "Usuario": "ESP32"
  },
  {
    "Folio": "VM-730",
    "Fecha": "2026-07-01",
    "Hora": "00:00:00",
    "Cliente": "Publico",
    "TipoDeCompra": "Vending",
    "TipoDePago": "Monedero",
    "Subtotal": 8.00,
    "Iva": 0.00,
    "Total": 8.00,
    "Efectivo": 8.00,
    "Tarjeta": 0.00,
    "Transferencia": 0.00,
    "Usuario": "ESP32"
  },
  {
    "Folio": "VM-731",
    "Fecha": "2026-07-01",
    "Hora": "00:00:00",
    "Cliente": "Publico",
    "TipoDeCompra": "Vending",
    "TipoDePago": "Monedero",
    "Subtotal": 8.00,
    "Iva": 0.00,
    "Total": 8.00,
    "Efectivo": 8.00,
    "Tarjeta": 0.00,
    "Transferencia": 0.00,
    "Usuario": "ESP32"
  },
  {
    "Folio": "VM-732",
    "Fecha": "2026-07-01",
    "Hora": "00:00:00",
    "Cliente": "Publico",
    "TipoDeCompra": "Vending",
    "TipoDePago": "Monedero",
    "Subtotal": 8.00,
    "Iva": 0.00,
    "Total": 8.00,
    "Efectivo": 8.00,
    "Tarjeta": 0.00,
    "Transferencia": 0.00,
    "Usuario": "ESP32"
  },
  {
    "Folio": "VM-733",
    "Fecha": "2026-07-01",
    "Hora": "00:00:00",
    "Cliente": "Publico",
    "TipoDeCompra": "Vending",
    "TipoDePago": "Monedero",
    "Subtotal": 8.00,
    "Iva": 0.00,
    "Total": 8.00,
    "Efectivo": 8.00,
    "Tarjeta": 0.00,
    "Transferencia": 0.00,
    "Usuario": "ESP32"
  },
  {
    "Folio": "VM-734",
    "Fecha": "2026-07-01",
    "Hora": "00:00:00",
    "Cliente": "Publico",
    "TipoDeCompra": "Vending",
    "TipoDePago": "Monedero",
    "Subtotal": 7.00,
    "Iva": 0.00,
    "Total": 7.00,
    "Efectivo": 7.00,
    "Tarjeta": 0.00,
    "Transferencia": 0.00,
    "Usuario": "ESP32"
  },
  {
    "Folio": "VM-735",
    "Fecha": "2026-07-01",
    "Hora": "00:00:00",
    "Cliente": "Publico",
    "TipoDeCompra": "Vending",
    "TipoDePago": "Monedero",
    "Subtotal": 7.00,
    "Iva": 0.00,
    "Total": 7.00,
    "Efectivo": 7.00,
    "Tarjeta": 0.00,
    "Transferencia": 0.00,
    "Usuario": "ESP32"
  },
  {
    "Folio": "VM-736",
    "Fecha": "2026-07-01",
    "Hora": "00:00:00",
    "Cliente": "Publico",
    "TipoDeCompra": "Vending",
    "TipoDePago": "Monedero",
    "Subtotal": 8.00,
    "Iva": 0.00,
    "Total": 8.00,
    "Efectivo": 8.00,
    "Tarjeta": 0.00,
    "Transferencia": 0.00,
    "Usuario": "ESP32"
  },
  {
    "Folio": "VM-737",
    "Fecha": "2026-07-01",
    "Hora": "00:00:00",
    "Cliente": "Publico",
    "TipoDeCompra": "Vending",
    "TipoDePago": "Monedero",
    "Subtotal": 7.00,
    "Iva": 0.00,
    "Total": 7.00,
    "Efectivo": 7.00,
    "Tarjeta": 0.00,
    "Transferencia": 0.00,
    "Usuario": "ESP32"
  },
  {
    "Folio": "VM-738",
    "Fecha": "2026-07-01",
    "Hora": "00:00:00",
    "Cliente": "Publico",
    "TipoDeCompra": "Vending",
    "TipoDePago": "Monedero",
    "Subtotal": 7.00,
    "Iva": 0.00,
    "Total": 7.00,
    "Efectivo": 7.00,
    "Tarjeta": 0.00,
    "Transferencia": 0.00,
    "Usuario": "ESP32"
  },
  {
    "Folio": "VM-739",
    "Fecha": "2026-07-01",
    "Hora": "00:00:00",
    "Cliente": "Publico",
    "TipoDeCompra": "Vending",
    "TipoDePago": "Monedero",
    "Subtotal": 8.00,
    "Iva": 0.00,
    "Total": 8.00,
    "Efectivo": 8.00,
    "Tarjeta": 0.00,
    "Transferencia": 0.00,
    "Usuario": "ESP32"
  },
  {
    "Folio": "VM-740",
    "Fecha": "2026-07-01",
    "Hora": "00:00:00",
    "Cliente": "Publico",
    "TipoDeCompra": "Vending",
    "TipoDePago": "Monedero",
    "Subtotal": 8.00,
    "Iva": 0.00,
    "Total": 8.00,
    "Efectivo": 8.00,
    "Tarjeta": 0.00,
    "Transferencia": 0.00,
    "Usuario": "ESP32"
  },
  {
    "Folio": "VMEN-2270",
    "Fecha": "2026-07-01",
    "Hora": "16:15:40",
    "Cliente": "N/A",
    "TipoDeCompra": "Menudeo",
    "TipoDePago": "Efectivo",
    "Subtotal": 20.00,
    "Iva": 0.00,
    "Total": 20.00,
    "Efectivo": 20.00,
    "Tarjeta": 0.00,
    "Transferencia": 0.00,
    "Usuario": "Gabriela Gracia"
  }
]